[
  {
    "year": 1990,
    "hydro_run": 0.0,
    "hydro_storage": -6102.0,
    "solar_pv": 0.0,
    "wind": 0.0,
    "waste_incineration": -9648.0,
    "ambient_heat": 0.0,
    "wood_electricity": 0.0,
    "wood_district_heat": 0.0,
    "biogas_agriculture": -9.0,
    "biogas_industry": 0.0,
    "biogas_sewage": -76.0,
    "biogas_landfill": -112.0,
    "waste_renewable_fire": -18.0
  },
  {
    "year": 1991,
    "hydro_run": 0.0,
    "hydro_storage": -7005.0,
    "solar_pv": 0.0,
    "wind": 0.0,
    "waste_incineration": -9603.0,
    "ambient_heat": 0.0,
    "wood_electricity": 0.0,
    "wood_district_heat": 0.0,
    "biogas_agriculture": -9.0,
    "biogas_industry": 0.0,
    "biogas_sewage": -76.0,
    "biogas_landfill": -139.0,
    "waste_renewable_fire": -15.0
  },
  {
    "year": 1992,
    "hydro_run": 0.0,
    "hydro_storage": -5177.0,
    "solar_pv": 0.0,
    "wind": 0.0,
    "waste_incineration": -9105.0,
    "ambient_heat": 0.0,
    "wood_electricity": 0.0,
    "wood_district_heat": 0.0,
    "biogas_agriculture": -9.0,
    "biogas_industry": -3.0,
    "biogas_sewage": -78.0,
    "biogas_landfill": -194.0,
    "waste_renewable_fire": -17.0
  },
  {
    "year": 1993,
    "hydro_run": 0.0,
    "hydro_storage": -4269.0,
    "solar_pv": 0.0,
    "wind": 0.0,
    "waste_incineration": -8932.0,
    "ambient_heat": 0.0,
    "wood_electricity": 0.0,
    "wood_district_heat": 0.0,
    "biogas_agriculture": -9.0,
    "biogas_industry": -4.0,
    "biogas_sewage": -78.0,
    "biogas_landfill": -264.0,
    "waste_renewable_fire": -18.0
  },
  {
    "year": 1994,
    "hydro_run": 0.0,
    "hydro_storage": -4576.0,
    "solar_pv": 0.0,
    "wind": 0.0,
    "waste_incineration": -8868.0,
    "ambient_heat": 0.0,
    "wood_electricity": 0.0,
    "wood_district_heat": 0.0,
    "biogas_agriculture": -9.0,
    "biogas_industry": -8.0,
    "biogas_sewage": -86.0,
    "biogas_landfill": -332.0,
    "waste_renewable_fire": -19.0
  },
  {
    "year": 1995,
    "hydro_run": 0.0,
    "hydro_storage": -5472.0,
    "solar_pv": 0.0,
    "wind": 0.0,
    "waste_incineration": -8552.0,
    "ambient_heat": 0.0,
    "wood_electricity": 0.0,
    "wood_district_heat": 0.0,
    "biogas_agriculture": -9.0,
    "biogas_industry": -11.0,
    "biogas_sewage": -89.0,
    "biogas_landfill": -302.0,
    "waste_renewable_fire": -22.0
  },
  {
    "year": 1996,
    "hydro_run": 0.0,
    "hydro_storage": -6314.0,
    "solar_pv": 0.0,
    "wind": 0.0,
    "waste_incineration": -8366.0,
    "ambient_heat": 0.0,
    "wood_electricity": 0.0,
    "wood_district_heat": 0.0,
    "biogas_agriculture": -10.0,
    "biogas_industry": -15.0,
    "biogas_sewage": -92.0,
    "biogas_landfill": -287.0,
    "waste_renewable_fire": -17.0
  },
  {
    "year": 1997,
    "hydro_run": 0.0,
    "hydro_storage": -5468.0,
    "solar_pv": 0.0,
    "wind": 0.0,
    "waste_incineration": -8855.0,
    "ambient_heat": 0.0,
    "wood_electricity": -3.0,
    "wood_district_heat": 0.0,
    "biogas_agriculture": -9.0,
    "biogas_industry": -20.0,
    "biogas_sewage": -97.0,
    "biogas_landfill": -284.0,
    "waste_renewable_fire": -26.0
  },
  {
    "year": 1998,
    "hydro_run": 0.0,
    "hydro_storage": -5832.0,
    "solar_pv": 0.0,
    "wind": 0.0,
    "waste_incineration": -9562.0,
    "ambient_heat": 0.0,
    "wood_electricity": -3.0,
    "wood_district_heat": 0.0,
    "biogas_agriculture": -12.0,
    "biogas_industry": -25.0,
    "biogas_sewage": -102.0,
    "biogas_landfill": -300.0,
    "waste_renewable_fire": -24.0
  },
  {
    "year": 1999,
    "hydro_run": 0.0,
    "hydro_storage": -5069.0,
    "solar_pv": 0.0,
    "wind": 0.0,
    "waste_incineration": -10265.0,
    "ambient_heat": 0.0,
    "wood_electricity": -4.0,
    "wood_district_heat": -14.0,
    "biogas_agriculture": -13.0,
    "biogas_industry": -26.0,
    "biogas_sewage": -110.0,
    "biogas_landfill": -299.0,
    "waste_renewable_fire": -27.0
  },
  {
    "year": 2000,
    "hydro_run": 0.0,
    "hydro_storage": -7106.0,
    "solar_pv": 0.0,
    "wind": 0.0,
    "waste_incineration": -11049.0,
    "ambient_heat": 0.0,
    "wood_electricity": -1.0,
    "wood_district_heat": -18.0,
    "biogas_agriculture": -17.0,
    "biogas_industry": -27.0,
    "biogas_sewage": -112.0,
    "biogas_landfill": -299.0,
    "waste_renewable_fire": -28.0
  },
  {
    "year": 2001,
    "hydro_run": 0.0,
    "hydro_storage": -7009.0,
    "solar_pv": 0.0,
    "wind": 0.0,
    "waste_incineration": -11659.0,
    "ambient_heat": 0.0,
    "wood_electricity": -2.0,
    "wood_district_heat": -16.0,
    "biogas_agriculture": -20.0,
    "biogas_industry": -34.0,
    "biogas_sewage": -135.0,
    "biogas_landfill": -267.0,
    "waste_renewable_fire": -26.0
  },
  {
    "year": 2002,
    "hydro_run": 0.0,
    "hydro_storage": -8705.0,
    "solar_pv": 0.0,
    "wind": 0.0,
    "waste_incineration": -11981.0,
    "ambient_heat": 0.0,
    "wood_electricity": -2.0,
    "wood_district_heat": -26.0,
    "biogas_agriculture": -24.0,
    "biogas_industry": -41.0,
    "biogas_sewage": -127.0,
    "biogas_landfill": -218.0,
    "waste_renewable_fire": -28.0
  },
  {
    "year": 2003,
    "hydro_run": 0.0,
    "hydro_storage": -10091.0,
    "solar_pv": 0.0,
    "wind": 0.0,
    "waste_incineration": -11490.0,
    "ambient_heat": 0.0,
    "wood_electricity": -5.0,
    "wood_district_heat": -29.0,
    "biogas_agriculture": -28.0,
    "biogas_industry": -43.0,
    "biogas_sewage": -127.0,
    "biogas_landfill": -230.0,
    "waste_renewable_fire": -30.0
  },
  {
    "year": 2004,
    "hydro_run": 0.0,
    "hydro_storage": -8759.0,
    "solar_pv": 0.0,
    "wind": 0.0,
    "waste_incineration": -11507.0,
    "ambient_heat": 0.0,
    "wood_electricity": -5.0,
    "wood_district_heat": -30.0,
    "biogas_agriculture": -35.0,
    "biogas_industry": -47.0,
    "biogas_sewage": -130.0,
    "biogas_landfill": -146.0,
    "waste_renewable_fire": -33.0
  },
  {
    "year": 2005,
    "hydro_run": 0.0,
    "hydro_storage": -9472.0,
    "solar_pv": 0.0,
    "wind": 0.0,
    "waste_incineration": -11996.0,
    "ambient_heat": 0.0,
    "wood_electricity": -4.0,
    "wood_district_heat": -43.0,
    "biogas_agriculture": -49.0,
    "biogas_industry": -56.0,
    "biogas_sewage": -128.0,
    "biogas_landfill": -114.0,
    "waste_renewable_fire": -31.0
  },
  {
    "year": 2006,
    "hydro_run": 0.0,
    "hydro_storage": -9792.0,
    "solar_pv": 0.0,
    "wind": 0.0,
    "waste_incineration": -13303.0,
    "ambient_heat": 0.0,
    "wood_electricity": -3.0,
    "wood_district_heat": -42.0,
    "biogas_agriculture": -81.0,
    "biogas_industry": -71.0,
    "biogas_sewage": -133.0,
    "biogas_landfill": -75.0,
    "waste_renewable_fire": -32.0
  },
  {
    "year": 2007,
    "hydro_run": 0.0,
    "hydro_storage": -7575.0,
    "solar_pv": 0.0,
    "wind": 0.0,
    "waste_incineration": -13242.0,
    "ambient_heat": 0.0,
    "wood_electricity": -176.0,
    "wood_district_heat": -42.0,
    "biogas_agriculture": -133.0,
    "biogas_industry": -83.0,
    "biogas_sewage": -137.0,
    "biogas_landfill": -52.0,
    "waste_renewable_fire": -36.0
  },
  {
    "year": 2008,
    "hydro_run": 0.0,
    "hydro_storage": -9666.0,
    "solar_pv": 0.0,
    "wind": 0.0,
    "waste_incineration": -12846.0,
    "ambient_heat": 0.0,
    "wood_electricity": -525.0,
    "wood_district_heat": -121.0,
    "biogas_agriculture": -169.0,
    "biogas_industry": -94.0,
    "biogas_sewage": -138.0,
    "biogas_landfill": -47.0,
    "waste_renewable_fire": -11.0
  },
  {
    "year": 2009,
    "hydro_run": 0.0,
    "hydro_storage": -9083.0,
    "solar_pv": 0.0,
    "wind": 0.0,
    "waste_incineration": -12948.0,
    "ambient_heat": 0.0,
    "wood_electricity": -629.0,
    "wood_district_heat": -234.0,
    "biogas_agriculture": -200.0,
    "biogas_industry": -127.0,
    "biogas_sewage": -139.0,
    "biogas_landfill": -39.0,
    "waste_renewable_fire": -10.0
  },
  {
    "year": 2010,
    "hydro_run": 0.0,
    "hydro_storage": -8978.0,
    "solar_pv": 0.0,
    "wind": 0.0,
    "waste_incineration": -12915.0,
    "ambient_heat": 0.0,
    "wood_electricity": -216.0,
    "wood_district_heat": -239.0,
    "biogas_agriculture": -238.0,
    "biogas_industry": -159.0,
    "biogas_sewage": -142.0,
    "biogas_landfill": -25.0,
    "waste_renewable_fire": -12.0
  },
  {
    "year": 2011,
    "hydro_run": 0.0,
    "hydro_storage": -8877.0,
    "solar_pv": 0.0,
    "wind": 0.0,
    "waste_incineration": -13234.0,
    "ambient_heat": 0.0,
    "wood_electricity": -610.0,
    "wood_district_heat": -314.0,
    "biogas_agriculture": -262.0,
    "biogas_industry": -189.0,
    "biogas_sewage": -144.0,
    "biogas_landfill": -24.0,
    "waste_renewable_fire": -10.0
  },
  {
    "year": 2012,
    "hydro_run": 0.0,
    "hydro_storage": -8679.0,
    "solar_pv": 0.0,
    "wind": 0.0,
    "waste_incineration": -13692.0,
    "ambient_heat": 0.0,
    "wood_electricity": -903.0,
    "wood_district_heat": -464.0,
    "biogas_agriculture": -319.0,
    "biogas_industry": -226.0,
    "biogas_sewage": -145.0,
    "biogas_landfill": -26.0,
    "waste_renewable_fire": -14.0
  },
  {
    "year": 2013,
    "hydro_run": 0.0,
    "hydro_storage": -7675.0,
    "solar_pv": 0.0,
    "wind": 0.0,
    "waste_incineration": -12541.0,
    "ambient_heat": 0.0,
    "wood_electricity": -913.0,
    "wood_district_heat": -515.0,
    "biogas_agriculture": -389.0,
    "biogas_industry": -233.0,
    "biogas_sewage": -145.0,
    "biogas_landfill": -22.0,
    "waste_renewable_fire": -14.0
  },
  {
    "year": 2014,
    "hydro_run": 0.0,
    "hydro_storage": -8478.0,
    "solar_pv": 0.0,
    "wind": 0.0,
    "waste_incineration": -12859.0,
    "ambient_heat": 0.0,
    "wood_electricity": -945.0,
    "wood_district_heat": -539.0,
    "biogas_agriculture": -445.0,
    "biogas_industry": -230.0,
    "biogas_sewage": -144.0,
    "biogas_landfill": -20.0,
    "waste_renewable_fire": -13.0
  },
  {
    "year": 2015,
    "hydro_run": 0.0,
    "hydro_storage": -8266.0,
    "solar_pv": 0.0,
    "wind": 0.0,
    "waste_incineration": -12950.0,
    "ambient_heat": 0.0,
    "wood_electricity": -254.0,
    "wood_district_heat": -459.0,
    "biogas_agriculture": -491.0,
    "biogas_industry": -239.0,
    "biogas_sewage": -142.0,
    "biogas_landfill": -14.0,
    "waste_renewable_fire": -15.0
  },
  {
    "year": 2016,
    "hydro_run": 0.0,
    "hydro_storage": -10519.0,
    "solar_pv": 0.0,
    "wind": 0.0,
    "waste_incineration": -13181.0,
    "ambient_heat": 0.0,
    "wood_electricity": -249.0,
    "wood_district_heat": -469.0,
    "biogas_agriculture": -578.0,
    "biogas_industry": -255.0,
    "biogas_sewage": -140.0,
    "biogas_landfill": -7.0,
    "waste_renewable_fire": -13.0
  },
  {
    "year": 2017,
    "hydro_run": 0.0,
    "hydro_storage": -14976.0,
    "solar_pv": 0.0,
    "wind": 0.0,
    "waste_incineration": -13142.0,
    "ambient_heat": 0.0,
    "wood_electricity": -453.0,
    "wood_district_heat": -492.0,
    "biogas_agriculture": -624.0,
    "biogas_industry": -256.0,
    "biogas_sewage": -142.0,
    "biogas_landfill": -4.0,
    "waste_renewable_fire": -13.0
  },
  {
    "year": 2018,
    "hydro_run": 0.0,
    "hydro_storage": -14353.0,
    "solar_pv": 0.0,
    "wind": 0.0,
    "waste_incineration": -13332.0,
    "ambient_heat": 0.0,
    "wood_electricity": -405.0,
    "wood_district_heat": -469.0,
    "biogas_agriculture": -544.0,
    "biogas_industry": -262.0,
    "biogas_sewage": -146.0,
    "biogas_landfill": -2.0,
    "waste_renewable_fire": -9.0
  },
  {
    "year": 2019,
    "hydro_run": 0.0,
    "hydro_storage": -14879.0,
    "solar_pv": 0.0,
    "wind": 0.0,
    "waste_incineration": -12994.0,
    "ambient_heat": 0.0,
    "wood_electricity": -398.0,
    "wood_district_heat": -641.0,
    "biogas_agriculture": -607.0,
    "biogas_industry": -267.0,
    "biogas_sewage": -148.0,
    "biogas_landfill": -4.0,
    "waste_renewable_fire": -9.0
  },
  {
    "year": 2020,
    "hydro_run": 0.0,
    "hydro_storage": -16053.0,
    "solar_pv": 0.0,
    "wind": 0.0,
    "waste_incineration": -13162.0,
    "ambient_heat": 0.0,
    "wood_electricity": -517.0,
    "wood_district_heat": -595.0,
    "biogas_agriculture": -736.0,
    "biogas_industry": -270.0,
    "biogas_sewage": -192.0,
    "biogas_landfill": -3.0,
    "waste_renewable_fire": -9.0
  },
  {
    "year": 2021,
    "hydro_run": 0.0,
    "hydro_storage": -14922.0,
    "solar_pv": 0.0,
    "wind": 0.0,
    "waste_incineration": -12416.0,
    "ambient_heat": 0.0,
    "wood_electricity": -547.0,
    "wood_district_heat": -647.0,
    "biogas_agriculture": -763.0,
    "biogas_industry": -277.0,
    "biogas_sewage": -199.0,
    "biogas_landfill": -4.0,
    "waste_renewable_fire": -10.0
  },
  {
    "year": 2022,
    "hydro_run": 0.0,
    "hydro_storage": -20042.0,
    "solar_pv": 0.0,
    "wind": 0.0,
    "waste_incineration": -12081.0,
    "ambient_heat": 0.0,
    "wood_electricity": -800.0,
    "wood_district_heat": -671.0,
    "biogas_agriculture": -781.0,
    "biogas_industry": -275.0,
    "biogas_sewage": -198.0,
    "biogas_landfill": -5.0,
    "waste_renewable_fire": -11.0
  },
  {
    "year": 2023,
    "hydro_run": 0.0,
    "hydro_storage": -19350.0,
    "solar_pv": 0.0,
    "wind": 0.0,
    "waste_incineration": -12150.0,
    "ambient_heat": 0.0,
    "wood_electricity": -1242.0,
    "wood_district_heat": -683.0,
    "biogas_agriculture": -762.0,
    "biogas_industry": -280.0,
    "biogas_sewage": -200.0,
    "biogas_landfill": -4.0,
    "waste_renewable_fire": -9.0
  },
  {
    "year": 2024,
    "hydro_run": 0.0,
    "hydro_storage": -17341.0,
    "solar_pv": 0.0,
    "wind": 0.0,
    "waste_incineration": -11879.0,
    "ambient_heat": 0.0,
    "wood_electricity": -1119.0,
    "wood_district_heat": -788.0,
    "biogas_agriculture": -790.0,
    "biogas_industry": -287.0,
    "biogas_sewage": -200.0,
    "biogas_landfill": -4.0,
    "waste_renewable_fire": -8.0
  }
]